{
  "modelVersion" : "2.3",
  "id" : "1PrikazPdfFajlovaForm",
  "name" : "1PrikazPdfFajlovaForm",
  "lastUpdate" : 1672856042572,
  "rows" : [
    [
      {
        "type" : "container",
        "dimension" : {
          "xs" : 12
        },
        "propertyValues" : { },
        "reference" : "f32d47a5-4357-4b79-8064-58e19048868a",
        "hasValidationError" : false,
        "id" : "pbContainer",
        "rows" : [
          [
            {
              "type" : "component",
              "dimension" : {
                "md" : 12,
                "sm" : 12,
                "xs" : 12,
                "lg" : 12
              },
              "propertyValues" : {
                "hidden" : {
                  "type" : "constant",
                  "value" : false
                },
                "level" : {
                  "type" : "constant",
                  "value" : "Level 1"
                },
                "cssClasses" : {
                  "type" : "constant",
                  "value" : ""
                },
                "text" : {
                  "type" : "interpolation",
                  "value" : "{{ task.displayName }}"
                },
                "alignment" : {
                  "type" : "constant",
                  "value" : "center"
                },
                "dimension" : {
                  "type" : "constant",
                  "value" : 12
                }
              },
              "reference" : "8e76e46f-3415-44aa-8851-8e46feb2069c",
              "hasValidationError" : false,
              "id" : "pbTitle",
              "description" : ""
            }
          ],
          [
            {
              "type" : "component",
              "dimension" : {
                "md" : 12,
                "sm" : 12,
                "xs" : 12,
                "lg" : 12
              },
              "propertyValues" : {
                "allowHtml" : {
                  "type" : "constant",
                  "value" : true
                },
                "labelHidden" : {
                  "type" : "constant",
                  "value" : true
                },
                "hidden" : {
                  "type" : "constant",
                  "value" : false
                },
                "cssClasses" : {
                  "type" : "constant",
                  "value" : ""
                },
                "label" : {
                  "type" : "interpolation"
                },
                "text" : {
                  "type" : "interpolation",
                  "value" : "{{ task.displayDescription }}"
                },
                "alignment" : {
                  "type" : "constant",
                  "value" : "left"
                },
                "dimension" : {
                  "type" : "constant",
                  "value" : 12
                }
              },
              "reference" : "f3333a64-a140-4aec-bf95-be5a8d84c3ad",
              "hasValidationError" : false,
              "id" : "pbText",
              "description" : ""
            }
          ]
        ]
      }
    ],
    [
      {
        "type" : "formContainer",
        "dimension" : {
          "xs" : 12
        },
        "propertyValues" : { },
        "reference" : "dccb13a0-20a2-4a12-a09d-c2fd30dbfadd",
        "hasValidationError" : false,
        "id" : "pbFormContainer",
        "container" : {
          "type" : "container",
          "dimension" : {
            "xs" : 12
          },
          "propertyValues" : { },
          "reference" : "6e2b63f1-a9bd-4a81-9152-3d250ddbcd26",
          "hasValidationError" : false,
          "id" : "pbContainer",
          "rows" : [
            [
              {
                "type" : "component",
                "dimension" : {
                  "xs" : 12,
                  "sm" : 12,
                  "md" : 12,
                  "lg" : 12
                },
                "propertyValues" : {
                  "cssClasses" : {
                    "type" : "constant",
                    "value" : ""
                  },
                  "hidden" : {
                    "type" : "constant",
                    "value" : false
                  },
                  "allowHTML" : {
                    "type" : "constant",
                    "value" : false
                  },
                  "text" : {
                    "type" : "interpolation",
                    "value" : "Zahtev za registraciju je poslat!"
                  },
                  "level" : {
                    "type" : "constant",
                    "value" : "Level 1"
                  },
                  "alignment" : {
                    "type" : "constant",
                    "value" : "center"
                  }
                },
                "reference" : "1bd0a734-38c9-4b8d-bec8-b77a2e04031a",
                "hasValidationError" : false,
                "id" : "pbTitle"
              }
            ],
            [
              {
                "type" : "component",
                "dimension" : {
                  "xs" : 12,
                  "sm" : 12,
                  "md" : 12,
                  "lg" : 12
                },
                "propertyValues" : {
                  "cssClasses" : {
                    "type" : "constant",
                    "value" : ""
                  },
                  "hidden" : {
                    "type" : "constant",
                    "value" : false
                  },
                  "allowHTML" : {
                    "type" : "constant",
                    "value" : false
                  },
                  "text" : {
                    "type" : "interpolation",
                    "value" : "Prikaz CV-ja i propratnog pisma u PDF formatu"
                  },
                  "level" : {
                    "type" : "constant",
                    "value" : "Level 3"
                  },
                  "alignment" : {
                    "type" : "constant",
                    "value" : "center"
                  }
                },
                "reference" : "727a8733-087f-4901-be23-6b47ab56483c",
                "hasValidationError" : false,
                "id" : "pbTitle"
              }
            ],
            [
              {
                "type" : "component",
                "dimension" : {
                  "xs" : 12,
                  "sm" : 12,
                  "md" : 12,
                  "lg" : 6
                },
                "propertyValues" : {
                  "cssClasses" : {
                    "type" : "constant",
                    "value" : ""
                  },
                  "hidden" : {
                    "type" : "constant",
                    "value" : false
                  },
                  "type" : {
                    "type" : "constant",
                    "value" : "Process document"
                  },
                  "url" : {
                    "type" : "constant",
                    "value" : ""
                  },
                  "document" : {
                    "type" : "variable",
                    "value" : "context.cvKanidataPdf_ref"
                  },
                  "showPreview" : {
                    "type" : "constant",
                    "value" : false
                  }
                },
                "reference" : "59fc8b48-73af-4e53-9d3f-3499996a6db5",
                "hasValidationError" : false,
                "id" : "pbFileViewer"
              }
            ],
            [
              {
                "type" : "component",
                "dimension" : {
                  "xs" : 12,
                  "sm" : 12,
                  "md" : 12,
                  "lg" : 12
                },
                "propertyValues" : {
                  "cssClasses" : {
                    "type" : "constant",
                    "value" : ""
                  },
                  "hidden" : {
                    "type" : "constant",
                    "value" : false
                  },
                  "type" : {
                    "type" : "constant",
                    "value" : "Process document"
                  },
                  "url" : {
                    "type" : "constant",
                    "value" : ""
                  },
                  "document" : {
                    "type" : "variable",
                    "value" : "context.propratnoPismoKandidataPdf_ref"
                  },
                  "showPreview" : {
                    "type" : "constant",
                    "value" : false
                  }
                },
                "reference" : "1b0efe67-38f2-4a4c-ad41-c9e492f6d25b",
                "hasValidationError" : false,
                "id" : "pbFileViewer"
              }
            ],
            [
              {
                "type" : "component",
                "dimension" : {
                  "md" : 12,
                  "sm" : 12,
                  "xs" : 12,
                  "lg" : 12
                },
                "propertyValues" : {
                  "removeItem" : {
                    "type" : "variable"
                  },
                  "hidden" : {
                    "type" : "constant",
                    "value" : false
                  },
                  "cssClasses" : {
                    "type" : "constant",
                    "value" : ""
                  },
                  "buttonStyle" : {
                    "type" : "constant",
                    "value" : "primary"
                  },
                  "label" : {
                    "type" : "interpolation",
                    "value" : "Submit"
                  },
                  "dataToSend" : {
                    "type" : "expression",
                    "value" : "formOutput"
                  },
                  "dataFromError" : {
                    "type" : "variable",
                    "value" : "formOutput._submitError"
                  },
                  "allowHTML" : {
                    "type" : "constant",
                    "value" : false
                  },
                  "labelHidden" : {
                    "type" : "constant",
                    "value" : false
                  },
                  "collectionPosition" : {
                    "type" : "constant"
                  },
                  "targetUrlOnSuccess" : {
                    "type" : "interpolation",
                    "value" : "/bonita"
                  },
                  "action" : {
                    "type" : "constant",
                    "value" : "Submit task"
                  },
                  "collectionToModify" : {
                    "type" : "variable"
                  },
                  "valueToAdd" : {
                    "type" : "expression"
                  },
                  "disabled" : {
                    "type" : "expression",
                    "value" : "$form.$invalid"
                  },
                  "alignment" : {
                    "type" : "constant",
                    "value" : "center"
                  },
                  "dimension" : {
                    "type" : "constant",
                    "value" : 12
                  },
                  "assign" : {
                    "type" : "constant",
                    "value" : false
                  },
                  "url" : {
                    "type" : "interpolation"
                  },
                  "responseStatusCode" : {
                    "type" : "variable"
                  },
                  "dataFromSuccess" : {
                    "type" : "variable"
                  },
                  "closeOnSuccess" : {
                    "type" : "constant",
                    "value" : false
                  },
                  "modalId" : {
                    "type" : "constant",
                    "value" : ""
                  }
                },
                "reference" : "255115b3-a5ff-4581-bba9-01046f6dea90",
                "hasValidationError" : false,
                "id" : "pbButton",
                "description" : ""
              }
            ],
            [
              {
                "type" : "component",
                "dimension" : {
                  "md" : 12,
                  "sm" : 12,
                  "xs" : 12,
                  "lg" : 12
                },
                "propertyValues" : {
                  "allowHTML" : {
                    "type" : "constant",
                    "value" : true
                  },
                  "allowHtml" : {
                    "type" : "constant",
                    "value" : true
                  },
                  "labelHidden" : {
                    "type" : "constant",
                    "value" : true
                  },
                  "hidden" : {
                    "type" : "expression",
                    "value" : "!formOutput._submitError.message"
                  },
                  "cssClasses" : {
                    "type" : "constant",
                    "value" : "alert alert-danger col-lg-6 col-lg-offset-3"
                  },
                  "label" : {
                    "type" : "interpolation"
                  },
                  "text" : {
                    "type" : "interpolation",
                    "value" : "<strong>Debug message</strong>\n<br/>\n{{formOutput._submitError.message}}\n{{submit_errors_list}}"
                  },
                  "alignment" : {
                    "type" : "constant",
                    "value" : "left"
                  },
                  "dimension" : {
                    "type" : "constant",
                    "value" : 12
                  }
                },
                "reference" : "eb60d89d-943e-429c-9d7e-02e5ce1b3b25",
                "hasValidationError" : false,
                "id" : "pbText",
                "description" : ""
              }
            ]
          ]
        }
      }
    ]
  ],
  "assets" : [
    {
      "id" : "3f18699a-5ef6-4116-92a3-a32607073557",
      "name" : "style.css",
      "type" : "css",
      "order" : 0,
      "external" : false
    },
    {
      "id" : "e5438585-67e8-42b3-a202-0fa05714e11f",
      "name" : "localization.json",
      "type" : "json",
      "order" : 0,
      "external" : false
    }
  ],
  "inactiveAssets" : [ ],
  "variables" : {
    "task" : {
      "type" : "url",
      "value" : [
        "../API/bpm/userTask/{{taskId}}"
      ],
      "exposed" : false
    },
    "submit_errors_list" : {
      "type" : "expression",
      "value" : [
        "if($data.formOutput && $data.formOutput._submitError && $data.formOutput._submitError.explanations){",
        "\tconst liElements = $data.formOutput._submitError.explanations",
        "\t\t.filter(cause => cause !== null)",
        "\t\t.map(cause => \"<li>\" + cause + \"</li>\")",
        "\t\t.join('');",
        "\tif(liElements){",
        "\t\treturn \"<ul>\" + liElements + \"</ul>\";",
        "\t}",
        "}"
      ],
      "exposed" : false
    },
    "formOutput" : {
      "type" : "expression",
      "value" : [
        "return {",
        "",
        "}"
      ],
      "exposed" : false
    },
    "context" : {
      "type" : "url",
      "value" : [
        "../API/bpm/userTask/{{taskId}}/context"
      ],
      "exposed" : false
    },
    "taskId" : {
      "type" : "urlparameter",
      "value" : [
        "id"
      ],
      "exposed" : false
    }
  },
  "hasValidationError" : false,
  "uuid" : "ce74a1b9-06f6-4781-bbfa-092c102e2ea9",
  "type" : "form",
  "description" : "Page generated with Bonita UI designer"
}